ttally/__init__.py
ttally/__main__.py
ttally/config.py
ttally/core.py
ttally/main.py
ttally/py.typed
ttally-0.1.4.dist-info/LICENSE
ttally-0.1.4.dist-info/METADATA
ttally-0.1.4.dist-info/WHEEL
ttally-0.1.4.dist-info/entry_points.txt
ttally-0.1.4.dist-info/top_level.txt
ttally-0.1.4.dist-info/RECORD
