Metadata-Version: 2.1
Name: ttally
Version: 0.1.4
Summary: interactive module to generate code/aliases to save things I do often
Home-page: https://github.com/seanbreckenridge/ttally
Author: Sean Breckenridge
Author-email: "seanbrecke@gmail.com"
License: MIT
Keywords: data,interactive
Classifier: License :: OSI Approved :: MIT License
Classifier: Programming Language :: Python
Classifier: Programming Language :: Python :: 3
Classifier: Programming Language :: Python :: 3 :: Only
Classifier: Programming Language :: Python :: 3.8
Classifier: Programming Language :: Python :: 3.9
Classifier: Programming Language :: Python :: 3.10
Classifier: Programming Language :: Python :: 3.11
Requires-Python: >=3.8
License-File: LICENSE
Requires-Dist: autotui >=0.4.6
Requires-Dist: click >=8.0
Requires-Dist: more-itertools >=8.0
Provides-Extra: testing
Requires-Dist: flake8 ; extra == 'testing'
Requires-Dist: mypy ; extra == 'testing'
